gecko_iot_client/__init__.py
gecko_iot_client/api.py
gecko_iot_client/changelog.py
gecko_iot_client/const.py
gecko_iot_client/py.typed
gecko_iot_client/models/__init__.py
gecko_iot_client/models/abstract_zone.py
gecko_iot_client/models/connectivity.py
gecko_iot_client/models/events.py
gecko_iot_client/models/flow_zone.py
gecko_iot_client/models/lighting_zone.py
gecko_iot_client/models/operation_mode.py
gecko_iot_client/models/operation_mode_controller.py
gecko_iot_client/models/temperature_control_zone.py
gecko_iot_client/models/zone_parser.py
gecko_iot_client/models/zone_types.py
gecko_iot_client/transporters/__init__.py
gecko_iot_client/transporters/connection_state.py
gecko_iot_client/transporters/exceptions.py
gecko_iot_client/transporters/logging_config.py
gecko_iot_client/transporters/token_manager.py
gecko_iot_client/transporters/mqtt/__init__.py
gecko_iot_client/transporters/mqtt/callback_registry.py
gecko_iot_client/transporters/mqtt/client.py
gecko_iot_client/transporters/mqtt/constants.py
gecko_iot_client/transporters/mqtt/reconnection_handler.py
gecko_iot_client/transporters/mqtt/token_manager.py
gecko_iot_client/transporters/mqtt/transporter.py
gecko_iot_client/transporters/mqtt/utils.py
gecko_iot_client-0.2.5.dist-info/licenses/LICENSE
gecko_iot_client-0.2.5.dist-info/METADATA
gecko_iot_client-0.2.5.dist-info/WHEEL
gecko_iot_client-0.2.5.dist-info/entry_points.txt
gecko_iot_client-0.2.5.dist-info/top_level.txt
gecko_iot_client-0.2.5.dist-info/RECORD
